MANIFEST.in
amon-agent
setup.py
amonagent/__init__.py
amonagent/check.py
amonagent/daemon.py
amonagent/defaults.py
amonagent/log.py
amonagent/plugin.py
amonagent/remote.py
amonagent/runner.py
amonagent/settings.py
amonagent/utils.py
amonagent.egg-info/PKG-INFO
amonagent.egg-info/SOURCES.txt
amonagent.egg-info/dependency_links.txt
amonagent.egg-info/not-zip-safe
amonagent.egg-info/requires.txt
amonagent.egg-info/top_level.txt
amonagent/modules/__init__.py
amonagent/modules/core.py
amonagent/modules/distro.py
amonagent/modules/packages.py
amonagent/modules/processes.py
tests/modules_core_test.py
tests/modules_core_test.pyc
tests/modules_distro_test.py
tests/modules_distro_test.pyc
tests/modules_packages_test.py
tests/modules_packages_test.pyc
tests/modules_processes_test.py
tests/modules_processes_test.pyc
tests/remote_test.pyc
tests/runner_test.py
tests/runner_test.pyc
tests/settings_test.py
tests/settings_test.pyc
tests/utils_test.pyc