Metadata-Version: 1.0
Name: amonagent
Version: 1.2
Summary: Linux system and process information collector
Home-page: UNKNOWN
Author: Martin Rusev
Author-email: martin@amon.cx
License: UNKNOWN
Platform: UNKNOWN
